genwebpush/__init__.py
genwebpush/__main__.py
genwebpush/core.py
genwebpush/models.py
genwebpush/assets/index.html
genwebpush/assets/manifest.json
genwebpush/assets/offline.html
genwebpush/assets/sw.js
genwebpush-0.1.14.dist-info/licenses/LICENSE.md
genwebpush-0.1.14.dist-info/METADATA
genwebpush-0.1.14.dist-info/WHEEL
genwebpush-0.1.14.dist-info/entry_points.txt
genwebpush-0.1.14.dist-info/top_level.txt
genwebpush-0.1.14.dist-info/RECORD
