Metadata-Version: 2.4
Name: genwebpush
Version: 0.1.14
Summary: A simple web push notification tool
Author-email: yniverz <hooped.dingos-81@icloud.com>
License-Expression: LicenseRef-NCPUL
Classifier: Programming Language :: Python
Requires-Python: >=3.8
License-File: LICENSE.md
Requires-Dist: Flask>=3.1.1
Requires-Dist: pywebpush>=2.0.3
Requires-Dist: cryptography>=45.0.2
Requires-Dist: requests>=2.32.3
Requires-Dist: python-dateutil>=2.9.0.post0
Requires-Dist: six>=1.17.0
Dynamic: license-file
